k8scontroller/__init__.py
k8scontroller/controller.py
k8scontroller/workqueue.py
k8scontroller/election/__init__.py
k8scontroller/election/elector.py
k8scontroller/election/record.py
k8scontroller/informer/__init__.py
k8scontroller/informer/cache.py
k8scontroller/informer/informer.py
k8scontroller/informer/lister.py
k8scontroller/informer/processor.py
k8scontroller/informer/watcher.py
pyk8s_controller-0.0.8.dist-info/LICENSE
pyk8s_controller-0.0.8.dist-info/METADATA
pyk8s_controller-0.0.8.dist-info/WHEEL
pyk8s_controller-0.0.8.dist-info/pbr.json
pyk8s_controller-0.0.8.dist-info/top_level.txt
pyk8s_controller-0.0.8.dist-info/RECORD
