Metadata-Version: 2.1
Name: pyk8s-controller
Version: 0.0.8
Summary: A Kubernetes Controller Framework for Python
Home-page: https://github.com/rmb938/pyk8s-controller
Author: Ryan Belgrave
Author-email: rmb1993@gmail.com
License: MIT
Platform: UNKNOWN
Classifier: Development Status :: 3 - Alpha
Classifier: Intended Audience :: Developers
Classifier: License :: OSI Approved :: MIT License
Classifier: Operating System :: OS Independent
Classifier: Programming Language :: Python
Classifier: Topic :: Software Development :: Libraries :: Application Frameworks
Requires-Dist: go-defer (>=1.0.1)
Requires-Dist: kubernetes (>=4.0.0)
